cov19/__init__.py
cov19/__main__.py
cov19/country.py
cov19/dataset.py
cov19/functions.py
cov19/models.py
cov19/region.py
cov19/stat.py
cov19-0.0.9.dist-info/LICENSE
cov19-0.0.9.dist-info/METADATA
cov19-0.0.9.dist-info/WHEEL
cov19-0.0.9.dist-info/top_level.txt
cov19-0.0.9.dist-info/RECORD
