Metadata-Version: 2.1
Name: cov19
Version: 0.0.9
Summary: Prediction for the spread of COVID-19 using Epidemiological Models
Home-page: https://github.com/emdemor/cov19
Author: Eduardo M. de Morais
Author-email: emdemor415@gmail.com
License: MIT License
Keywords: covid-19
Platform: UNKNOWN
Requires-Dist: numpy
Requires-Dist: scipy
Requires-Dist: pandas
Requires-Dist: pygtc
Requires-Dist: setuptools
Requires-Dist: tqdm
